cloudtools/__init__.py
cloudtools/client.py
cloudtools/config.py
cloudtools/constants.py
cloudtools/context.py
cloudtools/eventbus.py
cloudtools/kv.py
cloudtools/laydata.py
cloudtools/logging_utils.py
cloudtools/router.py
cloudtools/service.py
cloudtools/table.py
cloudtools/runtime/__init__.py
cloudtools/runtime/base.py
cloudtools/runtime/defaults.py
cloudtools/runtime/queue.py
cloudtools/runtime/workflow_context.py
cloudtools_sdk-0.4.0.dist-info/METADATA
cloudtools_sdk-0.4.0.dist-info/WHEEL
cloudtools_sdk-0.4.0.dist-info/top_level.txt
cloudtools_sdk-0.4.0.dist-info/RECORD
